MANIFEST.in
setup.py
keyword_zju/Function.py
keyword_zju/TFIDF.py
keyword_zju/TextRank.py
keyword_zju/__init__.py
keyword_zju/algorithm.py
keyword_zju/compoundBlackList.txt
keyword_zju/idf_5000.txt
keyword_zju/keywordBlackList.txt
keyword_zju/service.py
keyword_zju/test.py
keyword_zju/tmp_compoundword_Dictionary.txt
keyword_zjuzx.egg-info/PKG-INFO
keyword_zjuzx.egg-info/SOURCES.txt
keyword_zjuzx.egg-info/dependency_links.txt
keyword_zjuzx.egg-info/top_level.txt